README
setup.py
h5browse/__init__.py
h5browse/datasetplot.py
h5browse/dirreader.py
h5browse/h5browse.py
h5browse/hdfattributemodel.py
h5browse/hdfattributewidget.py
h5browse/hdfdatasetmodel.py
h5browse/hdfdatasetwidget.py
h5browse/hdftreemodel.py
h5browse/hdftreewidget.py
h5browse.egg-info/PKG-INFO
h5browse.egg-info/SOURCES.txt
h5browse.egg-info/dependency_links.txt
h5browse.egg-info/entry_points.txt
h5browse.egg-info/not-zip-safe
h5browse.egg-info/requires.txt
h5browse.egg-info/top_level.txt