Metadata-Version: 1.1
Name: h5browse
Version: 0.2
Summary: h5browse is a utility for browsing HDF5 files.
Home-page: UNKNOWN
Author: Subhasis Ray
Author-email: lastname dot firstname at gmail dot com
License: GPL
Keywords: hdf5 data plotting analysis
Platform: UNKNOWN
Classifier: Development Status :: 3 - Alpha
Classifier: Environment :: X11 Applications :: Qt
Classifier: Programming Language :: Python
Classifier: License :: OSI Approved :: GNU General Public License v3 or later (GPLv3+)
Classifier: Intended Audience :: Science/Research
Classifier: Natural Language :: English
Classifier: Operating System :: OS Independent
Classifier: Topic :: Scientific/Engineering :: Visualization
